<?xml version="1.0" encoding="UTF-8" ?>
<?xml-stylesheet type="text/xsl" href="https://portal.rosreestr.ru/xsl/GKN/KPT/10/common.xsl"?>
<KPT xmlns:ns2="urn://x-artefacts-rosreestr-ru/commons/complex-types/address-output/4.0.1"
xmlns:ns3="urn://x-artefacts-rosreestr-ru/commons/complex-types/entity-spatial/5.0.1"
xmlns:ns4="urn://x-artefacts-rosreestr-ru/commons/complex-types/parameters-oks/2.0.1"
xmlns:ns5="urn://x-artefacts-rosreestr-ru/commons/complex-types/document-output/4.0.1"
xmlns:ns6="urn://x-artefacts-rosreestr-ru/commons/complex-types/certification-doc/1.0"
xmlns:ns7="urn://x-artefacts-smev-gov-ru/supplementary/commons/1.0.1"
xmlns="urn://x-artefacts-rosreestr-ru/outgoing/kpt/10.0.1">
<CadastralBlocks>
<CadastralBlock CadastralNumber="54:35:064720">
<Area>
<Total>0</Total>
<Unit>059</Unit>
</Area><Parcels><Parcel CadastralNumber="54:35:064720:10" State="01" DateCreated="2007-06-22" >
<Area>
<Area>6</Area>
<Unit>055</Unit>
<Inaccuracy>0.2</Inaccuracy>
</Area>
<Name>01</Name>
<Location>
<inBounds>0</inBounds>
<Placed>К1</Placed>
<Elaboration>
<ReferenceMark>жилой дом</ReferenceMark>
<Distance>77 м</Distance>
<Direction>северо-запад</Direction>
</Elaboration>
<Address> <ns2:OKATO>50401377000</ns2:OKATO>
<ns2:KLADR>54000001000101300</ns2:KLADR>
<ns2:Region>54</ns2:Region>
<ns2:City Name="Новосибирск" Type="г" />
<ns2:Street Name="Плахотного" Type="ул" />
<ns2:Level1 Type="д" Value="74" />
<ns2:Note>обл. Новосибирская, г. Новосибирск, ул. Плахотного, дом 74</ns2:Note>
</Address>
</Location>
<Category>003002000000</Category>
<Utilization Utilization="142002000000" ByDoc="для размещения и эксплуатации торгового киоска в составе остановочного комплекса" />
<CadastralCost Value="42156.06" Unit="383" />
<EntitySpatial EntSys="ID0" >
<ns3:SpatialElement >
<ns3:SpelementUnit TypeUnit="Точка" SuNmb="1" >
<ns3:Ordinate X="483228.11" Y="4193140.12" OrdNmb="1" DeltaGeopoint="0.3" />
</ns3:SpelementUnit>
<ns3:SpelementUnit TypeUnit="Точка" SuNmb="2" >
<ns3:Ordinate X="483228.31" Y="4193143.11" OrdNmb="1" DeltaGeopoint="0.3" />
</ns3:SpelementUnit>
<ns3:SpelementUnit TypeUnit="Точка" SuNmb="3" >
<ns3:Ordinate X="483226.32" Y="4193143.25" OrdNmb="1" DeltaGeopoint="0.3" />
</ns3:SpelementUnit>
<ns3:SpelementUnit TypeUnit="Точка" SuNmb="4" >
<ns3:Ordinate X="483226.12" Y="4193140.25" OrdNmb="1" DeltaGeopoint="0.3" />
</ns3:SpelementUnit>
<ns3:SpelementUnit TypeUnit="Точка" SuNmb="5" >
<ns3:Ordinate X="483227.11" Y="4193140.19" OrdNmb="1" DeltaGeopoint="0.3" />
</ns3:SpelementUnit>
<ns3:SpelementUnit TypeUnit="Точка" SuNmb="1" >
<ns3:Ordinate X="483228.11" Y="4193140.12" OrdNmb="1" DeltaGeopoint="0.3" />
</ns3:SpelementUnit>
</ns3:SpatialElement>
</EntitySpatial>
</Parcel><Parcel CadastralNumber="54:35:064720:11" State="06" DateCreated="2008-07-04" >
<Area>
<Area>4111</Area>
<Unit>055</Unit>
<Inaccuracy>6</Inaccuracy>
</Area>
<Name>01</Name>
<Location>
<Address> <ns2:OKATO>50401377000</ns2:OKATO>
<ns2:KLADR>54000001000097100</ns2:KLADR>
<ns2:Region>54</ns2:Region>
<ns2:City Name="Новосибирск" Type="г" />
<ns2:Street Name="Пархоменко" Type="ул" />
<ns2:Note>обл. Новосибирская, г. Новосибирск, ул. Пархоменко</ns2:Note>
</Address>
</Location>
<Category>003002000000</Category>
<Utilization Utilization="142002000000" ByDoc="магазины продовольственных, промышленных и смешанных товаров, торговые комплексы, торговые центры" />
<CadastralCost Value="21690000" Unit="383" />
<EntitySpatial EntSys="ID0" >
<ns3:SpatialElement >
<ns3:SpelementUnit TypeUnit="Точка" SuNmb="1" >
<ns3:Ordinate X="483215.65" Y="4193054.29" OrdNmb="1" DeltaGeopoint="0.3" GeopointZacrep="Закрепление отсутствует" />
</ns3:SpelementUnit>
<ns3:SpelementUnit TypeUnit="Точка" SuNmb="2" >
<ns3:Ordinate X="483214.99" Y="4193054.33" OrdNmb="1" DeltaGeopoint="0.3" GeopointZacrep="Закрепление отсутствует" />
</ns3:SpelementUnit>
<ns3:SpelementUnit TypeUnit="Точка" SuNmb="3" >
<ns3:Ordinate X="483213.53" Y="4193054.44" OrdNmb="1" DeltaGeopoint="0.3" GeopointZacrep="Закрепление отсутствует" />
</ns3:SpelementUnit>
<ns3:SpelementUnit TypeUnit="Точка" SuNmb="4" >
<ns3:Ordinate X="483180.73" Y="4193056.79" OrdNmb="1" DeltaGeopoint="0.3" GeopointZacrep="Закрепление отсутствует" />
</ns3:SpelementUnit>
<ns3:SpelementUnit TypeUnit="Точка" SuNmb="5" >
<ns3:Ordinate X="483182.42" Y="4193083.59" OrdNmb="1" DeltaGeopoint="0.3" GeopointZacrep="Закрепление отсутствует" />
</ns3:SpelementUnit>
<ns3:SpelementUnit TypeUnit="Точка" SuNmb="6" >
<ns3:Ordinate X="483186.09" Y="4193141.93" OrdNmb="1" DeltaGeopoint="0.3" GeopointZacrep="Закрепление отсутствует" />
</ns3:SpelementUnit>
<ns3:SpelementUnit TypeUnit="Точка" SuNmb="7" >
<ns3:Ordinate X="483187.97" Y="4193171.87" OrdNmb="1" DeltaGeopoint="0.3" GeopointZacrep="Закрепление отсутствует" />
</ns3:SpelementUnit>
<ns3:SpelementUnit TypeUnit="Точка" SuNmb="8" >
<ns3:Ordinate X="483211.95" Y="4193170.78" OrdNmb="1" DeltaGeopoint="0.3" GeopointZacrep="Закрепление отсутствует" />
</ns3:SpelementUnit>
<ns3:SpelementUnit TypeUnit="Точка" SuNmb="9" >
<ns3:Ordinate X="483220.67" Y="4193170.38" OrdNmb="1" DeltaGeopoint="0.3" GeopointZacrep="Закрепление отсутствует" />
</ns3:SpelementUnit>
<ns3:SpelementUnit TypeUnit="Точка" SuNmb="10" >
<ns3:Ordinate X="483223.95" Y="4193170.2" OrdNmb="1" DeltaGeopoint="0.3" GeopointZacrep="Закрепление отсутствует" />
</ns3:SpelementUnit>
<ns3:SpelementUnit TypeUnit="Точка" SuNmb="11" >
<ns3:Ordinate X="483223.22" Y="4193159.94" OrdNmb="1" DeltaGeopoint="0.3" GeopointZacrep="Закрепление отсутствует" />
</ns3:SpelementUnit>
<ns3:SpelementUnit TypeUnit="Точка" SuNmb="12" >
<ns3:Ordinate X="483222.18" Y="4193145.45" OrdNmb="1" DeltaGeopoint="0.3" GeopointZacrep="Закрепление отсутствует" />
</ns3:SpelementUnit>
<ns3:SpelementUnit TypeUnit="Точка" SuNmb="13" >
<ns3:Ordinate X="483221.22" Y="4193132" OrdNmb="1" DeltaGeopoint="0.3" GeopointZacrep="Закрепление отсутствует" />
</ns3:SpelementUnit>
<ns3:SpelementUnit TypeUnit="Точка" SuNmb="14" >
<ns3:Ordinate X="483217.18" Y="4193075.64" OrdNmb="1" DeltaGeopoint="0.3" GeopointZacrep="Закрепление отсутствует" />
</ns3:SpelementUnit>
<ns3:SpelementUnit TypeUnit="Точка" SuNmb="15" >
<ns3:Ordinate X="483217.01" Y="4193073.25" OrdNmb="1" DeltaGeopoint="0.3" GeopointZacrep="Закрепление отсутствует" />
</ns3:SpelementUnit>
<ns3:SpelementUnit TypeUnit="Точка" SuNmb="16" >
<ns3:Ordinate X="483216.52" Y="4193066.44" OrdNmb="1" DeltaGeopoint="0.3" GeopointZacrep="Закрепление отсутствует" />
</ns3:SpelementUnit>
<ns3:SpelementUnit TypeUnit="Точка" SuNmb="17" >
<ns3:Ordinate X="483215.98" Y="4193058.87" OrdNmb="1" DeltaGeopoint="0.3" GeopointZacrep="Закрепление отсутствует" />
</ns3:SpelementUnit>
<ns3:SpelementUnit TypeUnit="Точка" SuNmb="1" >
<ns3:Ordinate X="483215.65" Y="4193054.29" OrdNmb="1" DeltaGeopoint="0.3" GeopointZacrep="Закрепление отсутствует" />
</ns3:SpelementUnit>
</ns3:SpatialElement>
</EntitySpatial>
</Parcel><Parcel CadastralNumber="54:35:064720:16" State="06" DateCreated="2011-09-29" >
<Area>
<Area>7550</Area>
<Unit>055</Unit>
<Inaccuracy>9</Inaccuracy>
</Area>
<Name>01</Name>
<Location>
<Address> <ns2:OKATO>50401377000</ns2:OKATO>
<ns2:KLADR>54000001000097100</ns2:KLADR>
<ns2:Region>54</ns2:Region>
<ns2:City Name="Новосибирск" Type="г" />
<ns2:Street Name="Пархоменко" Type="ул" />
<ns2:Note>Новосибирская область, г Новосибирск, ул Пархоменко</ns2:Note>
</Address>
</Location>
<Category>003002000000</Category>
<Utilization Utilization="142001020300" ByDoc="многоквартирные 14-18-этажные дома, в том числе с помещениями общественного назначения, автостоянками; трансформаторные подстанции" />
<CadastralCost Value="44420878" Unit="383" />
<EntitySpatial EntSys="ID0" >
<ns3:SpatialElement >
<ns3:SpelementUnit TypeUnit="Точка" SuNmb="1" >
<ns3:Ordinate X="483192.28" Y="4192757.57" OrdNmb="1" DeltaGeopoint="0.03" GeopointZacrep="Закрепление отсутствует" />
</ns3:SpelementUnit>
<ns3:SpelementUnit TypeUnit="Точка" SuNmb="2" >
<ns3:Ordinate X="483192.73" Y="4192763.97" OrdNmb="1" DeltaGeopoint="0.03" GeopointZacrep="Закрепление отсутствует" />
</ns3:SpelementUnit>
<ns3:SpelementUnit TypeUnit="Точка" SuNmb="3" >
<ns3:Ordinate X="483206.28" Y="4192953.38" OrdNmb="1" DeltaGeopoint="0.03" GeopointZacrep="Закрепление отсутствует" />
</ns3:SpelementUnit>
<ns3:SpelementUnit TypeUnit="Точка" SuNmb="4" >
<ns3:Ordinate X="483170.71" Y="4192955.65" OrdNmb="1" DeltaGeopoint="0.03" GeopointZacrep="Закрепление отсутствует" />
</ns3:SpelementUnit>
<ns3:SpelementUnit TypeUnit="Точка" SuNmb="5" >
<ns3:Ordinate X="483164" Y="4192956.08" OrdNmb="1" DeltaGeopoint="0.03" GeopointZacrep="Закрепление отсутствует" />
</ns3:SpelementUnit>
<ns3:SpelementUnit TypeUnit="Точка" SuNmb="6" >
<ns3:Ordinate X="483164.24" Y="4192933.85" OrdNmb="1" DeltaGeopoint="0.03" GeopointZacrep="Закрепление отсутствует" />
</ns3:SpelementUnit>
<ns3:SpelementUnit TypeUnit="Точка" SuNmb="7" >
<ns3:Ordinate X="483161.65" Y="4192922.43" OrdNmb="1" DeltaGeopoint="0.03" GeopointZacrep="Закрепление отсутствует" />
</ns3:SpelementUnit>
<ns3:SpelementUnit TypeUnit="Точка" SuNmb="8" >
<ns3:Ordinate X="483157.46" Y="4192920.67" OrdNmb="1" DeltaGeopoint="0.03" GeopointZacrep="Закрепление отсутствует" />
</ns3:SpelementUnit>
<ns3:SpelementUnit TypeUnit="Точка" SuNmb="9" >
<ns3:Ordinate X="483154.13" Y="4192916.96" OrdNmb="1" DeltaGeopoint="0.03" GeopointZacrep="Закрепление отсутствует" />
</ns3:SpelementUnit>
<ns3:SpelementUnit TypeUnit="Точка" SuNmb="10" >
<ns3:Ordinate X="483152" Y="4192911.11" OrdNmb="1" DeltaGeopoint="0.03" GeopointZacrep="Закрепление отсутствует" />
</ns3:SpelementUnit>
<ns3:SpelementUnit TypeUnit="Точка" SuNmb="11" >
<ns3:Ordinate X="483154.7" Y="4192903.46" OrdNmb="1" DeltaGeopoint="0.03" GeopointZacrep="Закрепление отсутствует" />
</ns3:SpelementUnit>
<ns3:SpelementUnit TypeUnit="Точка" SuNmb="12" >
<ns3:Ordinate X="483161.21" Y="4192903.4" OrdNmb="1" DeltaGeopoint="0.03" GeopointZacrep="Закрепление отсутствует" />
</ns3:SpelementUnit>
<ns3:SpelementUnit TypeUnit="Точка" SuNmb="13" >
<ns3:Ordinate X="483161.1" Y="4192896.21" OrdNmb="1" DeltaGeopoint="0.03" GeopointZacrep="Закрепление отсутствует" />
</ns3:SpelementUnit>
<ns3:SpelementUnit TypeUnit="Точка" SuNmb="14" >
<ns3:Ordinate X="483157.98" Y="4192896.37" OrdNmb="1" DeltaGeopoint="0.03" GeopointZacrep="Закрепление отсутствует" />
</ns3:SpelementUnit>
<ns3:SpelementUnit TypeUnit="Точка" SuNmb="15" >
<ns3:Ordinate X="483153.59" Y="4192893.92" OrdNmb="1" DeltaGeopoint="0.03" GeopointZacrep="Закрепление отсутствует" />
</ns3:SpelementUnit>
<ns3:SpelementUnit TypeUnit="Точка" SuNmb="16" >
<ns3:Ordinate X="483154.44" Y="4192875.99" OrdNmb="1" DeltaGeopoint="0.03" GeopointZacrep="Закрепление отсутствует" />
</ns3:SpelementUnit>
<ns3:SpelementUnit TypeUnit="Точка" SuNmb="17" >
<ns3:Ordinate X="483167.52" Y="4192874.68" OrdNmb="1" DeltaGeopoint="0.03" GeopointZacrep="Закрепление отсутствует" />
</ns3:SpelementUnit>
<ns3:SpelementUnit TypeUnit="Точка" SuNmb="18" >
<ns3:Ordinate X="483168.57" Y="4192874.57" OrdNmb="1" DeltaGeopoint="0.03" GeopointZacrep="Закрепление отсутствует" />
</ns3:SpelementUnit>
<ns3:SpelementUnit TypeUnit="Точка" SuNmb="19" >
<ns3:Ordinate X="483171.9" Y="4192875.1" OrdNmb="1" DeltaGeopoint="0.03" GeopointZacrep="Закрепление отсутствует" />
</ns3:SpelementUnit>
<ns3:SpelementUnit TypeUnit="Точка" SuNmb="20" >
<ns3:Ordinate X="483173.7" Y="4192864.08" OrdNmb="1" DeltaGeopoint="0.03" GeopointZacrep="Закрепление отсутствует" />
</ns3:SpelementUnit>
<ns3:SpelementUnit TypeUnit="Точка" SuNmb="21" >
<ns3:Ordinate X="483172.31" Y="4192848.47" OrdNmb="1" DeltaGeopoint="0.03" GeopointZacrep="Закрепление отсутствует" />
</ns3:SpelementUnit>
<ns3:SpelementUnit TypeUnit="Точка" SuNmb="22" >
<ns3:Ordinate X="483166.52" Y="4192849.15" OrdNmb="1" DeltaGeopoint="0.03" GeopointZacrep="Закрепление отсутствует" />
</ns3:SpelementUnit>
<ns3:SpelementUnit TypeUnit="Точка" SuNmb="23" >
<ns3:Ordinate X="483164.6" Y="4192849.37" OrdNmb="1" DeltaGeopoint="0.03" GeopointZacrep="Закрепление отсутствует" />
</ns3:SpelementUnit>
<ns3:SpelementUnit TypeUnit="Точка" SuNmb="24" >
<ns3:Ordinate X="483162.81" Y="4192833.5" OrdNmb="1" DeltaGeopoint="0.03" GeopointZacrep="Закрепление отсутствует" />
</ns3:SpelementUnit>
<ns3:SpelementUnit TypeUnit="Точка" SuNmb="25" >
<ns3:Ordinate X="483162.82" Y="4192832.32" OrdNmb="1" DeltaGeopoint="0.03" GeopointZacrep="Закрепление отсутствует" />
</ns3:SpelementUnit>
<ns3:SpelementUnit TypeUnit="Точка" SuNmb="26" >
<ns3:Ordinate X="483165.85" Y="4192831.75" OrdNmb="1" DeltaGeopoint="0.03" GeopointZacrep="Закрепление отсутствует" />
</ns3:SpelementUnit>
<ns3:SpelementUnit TypeUnit="Точка" SuNmb="27" >
<ns3:Ordinate X="483166.45" Y="4192831.63" OrdNmb="1" DeltaGeopoint="0.03" GeopointZacrep="Закрепление отсутствует" />
</ns3:SpelementUnit>
<ns3:SpelementUnit TypeUnit="Точка" SuNmb="28" >
<ns3:Ordinate X="483166.05" Y="4192827.37" OrdNmb="1" DeltaGeopoint="0.03" GeopointZacrep="Закрепление отсутствует" />
</ns3:SpelementUnit>
<ns3:SpelementUnit TypeUnit="Точка" SuNmb="29" >
<ns3:Ordinate X="483165.63" Y="4192826.3" OrdNmb="1" DeltaGeopoint="0.03" GeopointZacrep="Закрепление отсутствует" />
</ns3:SpelementUnit>
<ns3:SpelementUnit TypeUnit="Точка" SuNmb="30" >
<ns3:Ordinate X="483162.21" Y="4192817.6" OrdNmb="1" DeltaGeopoint="0.03" GeopointZacrep="Закрепление отсутствует" />
</ns3:SpelementUnit>
<ns3:SpelementUnit TypeUnit="Точка" SuNmb="31" >
<ns3:Ordinate X="483159.12" Y="4192814.4" OrdNmb="1" DeltaGeopoint="0.03" GeopointZacrep="Закрепление отсутствует" />
</ns3:SpelementUnit>
<ns3:SpelementUnit TypeUnit="Точка" SuNmb="32" >
<ns3:Ordinate X="483145.63" Y="4192815.89" OrdNmb="1" DeltaGeopoint="0.03" GeopointZacrep="Закрепление отсутствует" />
</ns3:SpelementUnit>
<ns3:SpelementUnit TypeUnit="Точка" SuNmb="33" >
<ns3:Ordinate X="483145.57" Y="4192795.64" OrdNmb="1" DeltaGeopoint="0.03" GeopointZacrep="Закрепление отсутствует" />
</ns3:SpelementUnit>
<ns3:SpelementUnit TypeUnit="Точка" SuNmb="34" >
<ns3:Ordinate X="483143.94" Y="4192782.69" OrdNmb="1" DeltaGeopoint="0.03" GeopointZacrep="Закрепление отсутствует" />
</ns3:SpelementUnit>
<ns3:SpelementUnit TypeUnit="Точка" SuNmb="35" >
<ns3:Ordinate X="483154.88" Y="4192783.16" OrdNmb="1" DeltaGeopoint="0.03" GeopointZacrep="Закрепление отсутствует" />
</ns3:SpelementUnit>
<ns3:SpelementUnit TypeUnit="Точка" SuNmb="36" >
<ns3:Ordinate X="483157.98" Y="4192783.2" OrdNmb="1" DeltaGeopoint="0.03" GeopointZacrep="Закрепление отсутствует" />
</ns3:SpelementUnit>
<ns3:SpelementUnit TypeUnit="Точка" SuNmb="37" >
<ns3:Ordinate X="483159.19" Y="4192788.37" OrdNmb="1" DeltaGeopoint="0.03" GeopointZacrep="Закрепление отсутствует" />
</ns3:SpelementUnit>
<ns3:SpelementUnit TypeUnit="Точка" SuNmb="38" >
<ns3:Ordinate X="483161.83" Y="4192787.88" OrdNmb="1" DeltaGeopoint="0.03" GeopointZacrep="Закрепление отсутствует" />
</ns3:SpelementUnit>
<ns3:SpelementUnit TypeUnit="Точка" SuNmb="39" >
<ns3:Ordinate X="483167.83" Y="4192786.85" OrdNmb="1" DeltaGeopoint="0.03" GeopointZacrep="Закрепление отсутствует" />
</ns3:SpelementUnit>
<ns3:SpelementUnit TypeUnit="Точка" SuNmb="40" >
<ns3:Ordinate X="483167.18" Y="4192777.47" OrdNmb="1" DeltaGeopoint="0.03" GeopointZacrep="Закрепление отсутствует" />
</ns3:SpelementUnit>
<ns3:SpelementUnit TypeUnit="Точка" SuNmb="41" >
<ns3:Ordinate X="483170.45" Y="4192777.54" OrdNmb="1" DeltaGeopoint="0.03" GeopointZacrep="Закрепление отсутствует" />
</ns3:SpelementUnit>
<ns3:SpelementUnit TypeUnit="Точка" SuNmb="42" >
<ns3:Ordinate X="483169.8" Y="4192765.31" OrdNmb="1" DeltaGeopoint="0.03" GeopointZacrep="Закрепление отсутствует" />
</ns3:SpelementUnit>
<ns3:SpelementUnit TypeUnit="Точка" SuNmb="43" >
<ns3:Ordinate X="483169.51" Y="4192759.72" OrdNmb="1" DeltaGeopoint="0.03" GeopointZacrep="Закрепление отсутствует" />
</ns3:SpelementUnit>
<ns3:SpelementUnit TypeUnit="Точка" SuNmb="44" >
<ns3:Ordinate X="483171.98" Y="4192759.5" OrdNmb="1" DeltaGeopoint="0.03" GeopointZacrep="Закрепление отсутствует" />
</ns3:SpelementUnit>
<ns3:SpelementUnit TypeUnit="Точка" SuNmb="45" >
<ns3:Ordinate X="483191.36" Y="4192757.66" OrdNmb="1" DeltaGeopoint="0.03" GeopointZacrep="Закрепление отсутствует" />
</ns3:SpelementUnit>
<ns3:SpelementUnit TypeUnit="Точка" SuNmb="1" >
<ns3:Ordinate X="483192.28" Y="4192757.57" OrdNmb="1" DeltaGeopoint="0.03" GeopointZacrep="Закрепление отсутствует" />
</ns3:SpelementUnit>
</ns3:SpatialElement>
</EntitySpatial>
</Parcel><Parcel CadastralNumber="54:35:064720:361" State="06" DateCreated="2012-11-15" >
<Area>
<Area>845</Area>
<Unit>055</Unit>
<Inaccuracy>7</Inaccuracy>
</Area>
<Name>01</Name>
<Location>
<Address> <ns2:OKATO>50401377000</ns2:OKATO>
<ns2:KLADR>54000001000097100</ns2:KLADR>
<ns2:Region>54</ns2:Region>
<ns2:City Name="Новосибирск" Type="г" />
<ns2:Street Name="Пархоменко" Type="ул" />
<ns2:Note>Новосибирская обл., г. Новосибирск, ул. Пархоменко</ns2:Note>
</Address>
</Location>
<Category>003002000000</Category>
<Utilization Utilization="142004050000" ByDoc="строительные площадки" />
<CadastralCost Value="873637.05" Unit="383" />
<EntitySpatial EntSys="ID0" >
<ns3:SpatialElement >
<ns3:SpelementUnit TypeUnit="Точка" SuNmb="1" >
<ns3:Ordinate X="483200.61" Y="4192838.34" OrdNmb="1" DeltaGeopoint="0.07" GeopointZacrep="Закрепление отсутствует" />
</ns3:SpelementUnit>
<ns3:SpelementUnit TypeUnit="Точка" SuNmb="2" >
<ns3:Ordinate X="483209.06" Y="4192843.53" OrdNmb="1" DeltaGeopoint="0.07" GeopointZacrep="Закрепление отсутствует" />
</ns3:SpelementUnit>
<ns3:SpelementUnit TypeUnit="Точка" SuNmb="3" >
<ns3:Ordinate X="483212.49" Y="4192897.46" OrdNmb="1" DeltaGeopoint="0.07" GeopointZacrep="Закрепление отсутствует" />
</ns3:SpelementUnit>
<ns3:SpelementUnit TypeUnit="Точка" SuNmb="4" >
<ns3:Ordinate X="483215.98" Y="4192945.57" OrdNmb="1" DeltaGeopoint="0.07" GeopointZacrep="Закрепление отсутствует" />
</ns3:SpelementUnit>
<ns3:SpelementUnit TypeUnit="Точка" SuNmb="5" >
<ns3:Ordinate X="483208.55" Y="4192951.55" OrdNmb="1" DeltaGeopoint="0.07" GeopointZacrep="Закрепление отсутствует" />
</ns3:SpelementUnit>
<ns3:SpelementUnit TypeUnit="Точка" SuNmb="1" >
<ns3:Ordinate X="483200.61" Y="4192838.34" OrdNmb="1" DeltaGeopoint="0.07" GeopointZacrep="Закрепление отсутствует" />
</ns3:SpelementUnit>
</ns3:SpatialElement>
</EntitySpatial>
</Parcel><Parcel CadastralNumber="54:35:064720:362" State="06" DateCreated="2012-11-15" >
<Area>
<Area>285</Area>
<Unit>055</Unit>
<Inaccuracy>4</Inaccuracy>
</Area>
<Name>01</Name>
<Location>
<Address> <ns2:OKATO>50401377000</ns2:OKATO>
<ns2:KLADR>54000001000097100</ns2:KLADR>
<ns2:Region>54</ns2:Region>
<ns2:City Name="Новосибирск" Type="г" />
<ns2:Street Name="Пархоменко" Type="ул" />
<ns2:Note>Новосибирская обл., г. Новосибирск, ул. Пархоменко</ns2:Note>
</Address>
</Location>
<Category>003002000000</Category>
<Utilization Utilization="143003020100" ByDoc="элементы обустройства автомобильных дорог; строительные площадки" />
<CadastralCost Value="294658.65" Unit="383" />
<EntitySpatial EntSys="ID0" >
<ns3:SpatialElement >
<ns3:SpelementUnit TypeUnit="Точка" SuNmb="1" >
<ns3:Ordinate X="483200.61" Y="4192838.34" OrdNmb="1" DeltaGeopoint="0.07" GeopointZacrep="Закрепление отсутствует" />
</ns3:SpelementUnit>
<ns3:SpelementUnit TypeUnit="Точка" SuNmb="2" >
<ns3:Ordinate X="483208.55" Y="4192951.55" OrdNmb="1" DeltaGeopoint="0.07" GeopointZacrep="Закрепление отсутствует" />
</ns3:SpelementUnit>
<ns3:SpelementUnit TypeUnit="Точка" SuNmb="3" >
<ns3:Ordinate X="483206.28" Y="4192953.38" OrdNmb="1" DeltaGeopoint="0.07" GeopointZacrep="Закрепление отсутствует" />
</ns3:SpelementUnit>
<ns3:SpelementUnit TypeUnit="Точка" SuNmb="4" >
<ns3:Ordinate X="483197.94" Y="4192836.69" OrdNmb="1" DeltaGeopoint="0.07" GeopointZacrep="Закрепление отсутствует" />
</ns3:SpelementUnit>
<ns3:SpelementUnit TypeUnit="Точка" SuNmb="1" >
<ns3:Ordinate X="483200.61" Y="4192838.34" OrdNmb="1" DeltaGeopoint="0.07" GeopointZacrep="Закрепление отсутствует" />
</ns3:SpelementUnit>
</ns3:SpatialElement>
</EntitySpatial>
</Parcel><Parcel CadastralNumber="54:35:064720:7" State="01" DateCreated="2005-10-11" >
<Area>
<Area>24</Area>
<Unit>055</Unit>
<Inaccuracy>0.5</Inaccuracy>
</Area>
<Name>01</Name>
<Location>
<inBounds>0</inBounds>
<Placed>Л2</Placed>
<Elaboration>
<ReferenceMark>жилой дом</ReferenceMark>
<Distance>40 м</Distance>
<Direction>север</Direction>
</Elaboration>
<Address> <ns2:OKATO>50401377000</ns2:OKATO>
<ns2:KLADR>54000001000097100</ns2:KLADR>
<ns2:Region>54</ns2:Region>
<ns2:City Name="Новосибирск" Type="г" />
<ns2:Street Name="Пархоменко" Type="ул" />
<ns2:Level1 Type="д" Value="104" />
<ns2:Note>обл. Новосибирская, г. Новосибирск, ул. Пархоменко, дом 104</ns2:Note>
</Address>
</Location>
<Category>003002000000</Category>
<Utilization Utilization="142002000000" ByDoc="для размещения и эксплуатации торгового павильона" />
<CadastralCost Value="168889.44" Unit="383" />
<EntitySpatial EntSys="ID0" >
<ns3:SpatialElement >
<ns3:SpelementUnit TypeUnit="Точка" SuNmb="1" >
<ns3:Ordinate X="483220.67" Y="4193170.38" OrdNmb="1" DeltaGeopoint="0.3" />
</ns3:SpelementUnit>
<ns3:SpelementUnit TypeUnit="Точка" SuNmb="2" >
<ns3:Ordinate X="483224.68" Y="4193170.16" OrdNmb="1" DeltaGeopoint="0.3" />
</ns3:SpelementUnit>
<ns3:SpelementUnit TypeUnit="Точка" SuNmb="3" >
<ns3:Ordinate X="483225.12" Y="4193176.18" OrdNmb="1" DeltaGeopoint="0.3" />
</ns3:SpelementUnit>
<ns3:SpelementUnit TypeUnit="Точка" SuNmb="4" >
<ns3:Ordinate X="483221.11" Y="4193176.47" OrdNmb="1" DeltaGeopoint="0.3" />
</ns3:SpelementUnit>
<ns3:SpelementUnit TypeUnit="Точка" SuNmb="1" >
<ns3:Ordinate X="483220.67" Y="4193170.38" OrdNmb="1" DeltaGeopoint="0.3" />
</ns3:SpelementUnit>
</ns3:SpatialElement>
</EntitySpatial>
</Parcel><Parcel CadastralNumber="54:35:064720:9" State="01" DateCreated="2007-05-10" >
<Area>
<Area>8</Area>
<Unit>055</Unit>
<Inaccuracy>0.3</Inaccuracy>
</Area>
<Name>01</Name>
<Location>
<inBounds>0</inBounds>
<Placed>Ж2</Placed>
<Elaboration>
<ReferenceMark>жилой дом</ReferenceMark>
<Distance>70 м</Distance>
<Direction>юго-восток</Direction>
</Elaboration>
<Address> <ns2:OKATO>50401377000</ns2:OKATO>
<ns2:KLADR>54000001000097100</ns2:KLADR>
<ns2:Region>54</ns2:Region>
<ns2:City Name="Новосибирск" Type="г" />
<ns2:Street Name="Пархоменко" Type="ул" />
<ns2:Level1 Type="д" Value="112" />
<ns2:Note>обл. Новосибирская, г. Новосибирск, ул. Пархоменко, дом 112</ns2:Note>
</Address>
</Location>
<Category>003002000000</Category>
<Utilization Utilization="142002000000" ByDoc="для размещения и эксплуатации торгового киоска" />
<CadastralCost Value="55939.76" Unit="383" />
<EntitySpatial EntSys="ID0" >
<ns3:SpatialElement >
<ns3:SpelementUnit TypeUnit="Точка" SuNmb="1" >
<ns3:Ordinate X="483218.84" Y="4193045.62" OrdNmb="1" DeltaGeopoint="0.3" />
</ns3:SpelementUnit>
<ns3:SpelementUnit TypeUnit="Точка" SuNmb="2" >
<ns3:Ordinate X="483219.13" Y="4193048.51" OrdNmb="1" DeltaGeopoint="0.3" />
</ns3:SpelementUnit>
<ns3:SpelementUnit TypeUnit="Точка" SuNmb="3" >
<ns3:Ordinate X="483216.45" Y="4193048.78" OrdNmb="1" DeltaGeopoint="0.3" />
</ns3:SpelementUnit>
<ns3:SpelementUnit TypeUnit="Точка" SuNmb="4" >
<ns3:Ordinate X="483216.16" Y="4193045.89" OrdNmb="1" DeltaGeopoint="0.3" />
</ns3:SpelementUnit>
<ns3:SpelementUnit TypeUnit="Точка" SuNmb="1" >
<ns3:Ordinate X="483218.84" Y="4193045.62" OrdNmb="1" DeltaGeopoint="0.3" />
</ns3:SpelementUnit>
</ns3:SpatialElement>
</EntitySpatial>
</Parcel></Parcels><ObjectsRealty><ObjectRealty>
<Building CadastralNumber="54:35:064720:17">
<ObjectType>002001002000</ObjectType>
<AssignationBuilding>204001000000</AssignationBuilding>
<Area>79.2</Area>
<Address>
<ns2:OKATO>50401377000</ns2:OKATO>
<ns2:KLADR>54000001000097100</ns2:KLADR>
<ns2:Region>54</ns2:Region>
<ns2:City Name="Новосибирск" Type="г" />
<ns2:Street Name="Пархоменко" Type="ул" />
<ns2:Level1 Type="д" Value="112" />
</Address>
<CadastralCost Value="1427924.52" Unit="383" />
</Building>
</ObjectRealty><ObjectRealty>
<Building CadastralNumber="54:35:064720:18">
<ObjectType>002001002000</ObjectType>
<AssignationBuilding>204003000000</AssignationBuilding>
<Area>20178</Area>
<Address>
<ns2:OKATO>50401377000</ns2:OKATO>
<ns2:KLADR>54000001000097100</ns2:KLADR>
<ns2:Region>54</ns2:Region>
<ns2:City Name="Новосибирск" Type="г" />
<ns2:Street Name="Пархоменко" Type="ул" />
<ns2:Level1 Type="д" Value="112" />
</Address>
<CadastralCost Value="1043547240.24" Unit="383" />
</Building>
</ObjectRealty><ObjectRealty>
<Building CadastralNumber="54:35:064720:19">
<ObjectType>002001002000</ObjectType>
<AssignationBuilding>204003000000</AssignationBuilding>
<Area>2734.2</Area>
<Address>
<ns2:OKATO>50401377000</ns2:OKATO>
<ns2:KLADR>54000001000097100</ns2:KLADR>
<ns2:Region>54</ns2:Region>
<ns2:City Name="Новосибирск" Type="г" />
<ns2:Street Name="Пархоменко" Type="ул" />
<ns2:Level1 Type="д" Value="74" />
</Address>
<CadastralCost Value="132058004.78" Unit="383" />
</Building>
</ObjectRealty><ObjectRealty>
<Building CadastralNumber="54:35:064720:20">
<ObjectType>002001002000</ObjectType>
<AssignationBuilding>204003000000</AssignationBuilding>
<Area>8011.5</Area>
<Address>
<ns2:OKATO>50401377000</ns2:OKATO>
<ns2:KLADR>54000001000097100</ns2:KLADR>
<ns2:Region>54</ns2:Region>
<ns2:City Name="Новосибирск" Type="г" />
<ns2:Street Name="Пархоменко" Type="ул" />
<ns2:Level1 Type="д" Value="102" />
</Address>
<CadastralCost Value="438940391.09" Unit="383" />
</Building>
</ObjectRealty><ObjectRealty>
<Building CadastralNumber="54:35:064720:418">
<ObjectType>002001002000</ObjectType>
<AssignationBuilding>204003000000</AssignationBuilding>
<Area>8610.2</Area>
<Address>
<ns2:OKATO>50401377000</ns2:OKATO>
<ns2:KLADR>54000001000097100</ns2:KLADR>
<ns2:PostalCode>630108</ns2:PostalCode>
<ns2:Region>54</ns2:Region>
<ns2:City Name="Новосибирск" Type="г" />
<ns2:Street Name="Пархоменко" Type="ул" />
<ns2:Level1 Type="д" Value="27" />
</Address>
<CadastralCost Value="508455643.64" Unit="383" />
<EntitySpatial EntSys="ID0" >
<ns3:SpatialElement >
<ns3:SpelementUnit TypeUnit="Точка" SuNmb="1" >
<ns3:Ordinate X="483195" Y="4192895.92" OrdNmb="1" DeltaGeopoint="0.03" />
</ns3:SpelementUnit>
<ns3:SpelementUnit TypeUnit="Точка" SuNmb="2" >
<ns3:Ordinate X="483196.39" Y="4192919.39" OrdNmb="1" DeltaGeopoint="0.03" />
</ns3:SpelementUnit>
<ns3:SpelementUnit TypeUnit="Точка" SuNmb="3" >
<ns3:Ordinate X="483173" Y="4192920.78" OrdNmb="1" DeltaGeopoint="0.03" />
</ns3:SpelementUnit>
<ns3:SpelementUnit TypeUnit="Точка" SuNmb="4" >
<ns3:Ordinate X="483171.6" Y="4192897.31" OrdNmb="1" DeltaGeopoint="0.03" />
</ns3:SpelementUnit>
<ns3:SpelementUnit TypeUnit="Точка" SuNmb="1" >
<ns3:Ordinate X="483195" Y="4192895.92" OrdNmb="1" DeltaGeopoint="0.03" />
</ns3:SpelementUnit>
</ns3:SpatialElement>
</EntitySpatial>
</Building>
</ObjectRealty><ObjectRealty>
<Building CadastralNumber="54:35:064720:555">
<ObjectType>002001002000</ObjectType>
<AssignationBuilding>204001000000</AssignationBuilding>
<Area>20</Area>
<Address>
<ns2:OKATO>50401377000</ns2:OKATO>
<ns2:KLADR>54000001000097100</ns2:KLADR>
<ns2:Region>54</ns2:Region>
<ns2:City Name="Новосибирск" Type="г" />
<ns2:Street Name="Пархоменко" Type="ул" />
<ns2:Level1 Type="д" Value="(29)" />
</Address>
<CadastralCost Value="474563" Unit="383" />
<EntitySpatial EntSys="ID0" >
<ns3:SpatialElement >
<ns3:SpelementUnit TypeUnit="Точка" SuNmb="1" >
<ns3:Ordinate X="483195.03" Y="4192947.99" OrdNmb="1" DeltaGeopoint="0.03" />
</ns3:SpelementUnit>
<ns3:SpelementUnit TypeUnit="Точка" SuNmb="2" >
<ns3:Ordinate X="483195.37" Y="4192953.12" OrdNmb="1" DeltaGeopoint="0.03" />
</ns3:SpelementUnit>
<ns3:SpelementUnit TypeUnit="Точка" SuNmb="3" >
<ns3:Ordinate X="483190.69" Y="4192953.48" OrdNmb="1" DeltaGeopoint="0.03" />
</ns3:SpelementUnit>
<ns3:SpelementUnit TypeUnit="Точка" SuNmb="4" >
<ns3:Ordinate X="483190.35" Y="4192948.35" OrdNmb="1" DeltaGeopoint="0.03" />
</ns3:SpelementUnit>
<ns3:SpelementUnit TypeUnit="Точка" SuNmb="1" >
<ns3:Ordinate X="483195.03" Y="4192947.99" OrdNmb="1" DeltaGeopoint="0.03" />
</ns3:SpelementUnit>
</ns3:SpatialElement>
</EntitySpatial>
</Building>
</ObjectRealty></ObjectsRealty><SpatialData>
<EntitySpatial EntSys="ID0" >
<ns3:SpatialElement >
<ns3:SpelementUnit TypeUnit="Точка" SuNmb="1" >
<ns3:Ordinate X="483224.7" Y="4192763.93" OrdNmb="1" />
</ns3:SpelementUnit>
<ns3:SpelementUnit TypeUnit="Точка" SuNmb="2" >
<ns3:Ordinate X="483218.01" Y="4192764.03" OrdNmb="1" />
</ns3:SpelementUnit>
<ns3:SpelementUnit TypeUnit="Точка" SuNmb="3" >
<ns3:Ordinate X="483217.71" Y="4192764.02" OrdNmb="1" />
</ns3:SpelementUnit>
<ns3:SpelementUnit TypeUnit="Точка" SuNmb="4" >
<ns3:Ordinate X="483219.97" Y="4192794.87" OrdNmb="1" />
</ns3:SpelementUnit>
<ns3:SpelementUnit TypeUnit="Точка" SuNmb="5" >
<ns3:Ordinate X="483201.02" Y="4192796.26" OrdNmb="1" />
</ns3:SpelementUnit>
<ns3:SpelementUnit TypeUnit="Точка" SuNmb="6" >
<ns3:Ordinate X="483198.66" Y="4192763.96" OrdNmb="1" />
</ns3:SpelementUnit>
<ns3:SpelementUnit TypeUnit="Точка" SuNmb="7" >
<ns3:Ordinate X="483193.23" Y="4192763.95" OrdNmb="1" />
</ns3:SpelementUnit>
<ns3:SpelementUnit TypeUnit="Точка" SuNmb="8" >
<ns3:Ordinate X="483192.73" Y="4192763.97" OrdNmb="1" />
</ns3:SpelementUnit>
<ns3:SpelementUnit TypeUnit="Точка" SuNmb="9" >
<ns3:Ordinate X="483192.28" Y="4192757.58" OrdNmb="1" />
</ns3:SpelementUnit>
<ns3:SpelementUnit TypeUnit="Точка" SuNmb="10" >
<ns3:Ordinate X="483191.36" Y="4192757.66" OrdNmb="1" />
</ns3:SpelementUnit>
<ns3:SpelementUnit TypeUnit="Точка" SuNmb="11" >
<ns3:Ordinate X="483171.98" Y="4192759.5" OrdNmb="1" />
</ns3:SpelementUnit>
<ns3:SpelementUnit TypeUnit="Точка" SuNmb="12" >
<ns3:Ordinate X="483169.51" Y="4192759.71" OrdNmb="1" />
</ns3:SpelementUnit>
<ns3:SpelementUnit TypeUnit="Точка" SuNmb="13" >
<ns3:Ordinate X="483169.8" Y="4192765.31" OrdNmb="1" />
</ns3:SpelementUnit>
<ns3:SpelementUnit TypeUnit="Точка" SuNmb="14" >
<ns3:Ordinate X="483168.03" Y="4192765.4" OrdNmb="1" />
</ns3:SpelementUnit>
<ns3:SpelementUnit TypeUnit="Точка" SuNmb="15" >
<ns3:Ordinate X="483163.6" Y="4192766.22" OrdNmb="1" />
</ns3:SpelementUnit>
<ns3:SpelementUnit TypeUnit="Точка" SuNmb="16" >
<ns3:Ordinate X="483163.57" Y="4192773.85" OrdNmb="1" />
</ns3:SpelementUnit>
<ns3:SpelementUnit TypeUnit="Точка" SuNmb="17" >
<ns3:Ordinate X="483163.3" Y="4192773.79" OrdNmb="1" />
</ns3:SpelementUnit>
<ns3:SpelementUnit TypeUnit="Точка" SuNmb="18" >
<ns3:Ordinate X="483163.61" Y="4192777.73" OrdNmb="1" />
</ns3:SpelementUnit>
<ns3:SpelementUnit TypeUnit="Точка" SuNmb="19" >
<ns3:Ordinate X="483167.18" Y="4192777.47" OrdNmb="1" />
</ns3:SpelementUnit>
<ns3:SpelementUnit TypeUnit="Точка" SuNmb="20" >
<ns3:Ordinate X="483167.83" Y="4192786.85" OrdNmb="1" />
</ns3:SpelementUnit>
<ns3:SpelementUnit TypeUnit="Точка" SuNmb="21" >
<ns3:Ordinate X="483161.83" Y="4192787.88" OrdNmb="1" />
</ns3:SpelementUnit>
<ns3:SpelementUnit TypeUnit="Точка" SuNmb="22" >
<ns3:Ordinate X="483159.19" Y="4192788.37" OrdNmb="1" />
</ns3:SpelementUnit>
<ns3:SpelementUnit TypeUnit="Точка" SuNmb="23" >
<ns3:Ordinate X="483157.98" Y="4192783.2" OrdNmb="1" />
</ns3:SpelementUnit>
<ns3:SpelementUnit TypeUnit="Точка" SuNmb="24" >
<ns3:Ordinate X="483154.88" Y="4192783.16" OrdNmb="1" />
</ns3:SpelementUnit>
<ns3:SpelementUnit TypeUnit="Точка" SuNmb="25" >
<ns3:Ordinate X="483143.94" Y="4192782.69" OrdNmb="1" />
</ns3:SpelementUnit>
<ns3:SpelementUnit TypeUnit="Точка" SuNmb="26" >
<ns3:Ordinate X="483145.57" Y="4192795.64" OrdNmb="1" />
</ns3:SpelementUnit>
<ns3:SpelementUnit TypeUnit="Точка" SuNmb="27" >
<ns3:Ordinate X="483145.63" Y="4192815.89" OrdNmb="1" />
</ns3:SpelementUnit>
<ns3:SpelementUnit TypeUnit="Точка" SuNmb="28" >
<ns3:Ordinate X="483159.12" Y="4192814.41" OrdNmb="1" />
</ns3:SpelementUnit>
<ns3:SpelementUnit TypeUnit="Точка" SuNmb="29" >
<ns3:Ordinate X="483162.21" Y="4192817.61" OrdNmb="1" />
</ns3:SpelementUnit>
<ns3:SpelementUnit TypeUnit="Точка" SuNmb="30" >
<ns3:Ordinate X="483165.64" Y="4192826.31" OrdNmb="1" />
</ns3:SpelementUnit>
<ns3:SpelementUnit TypeUnit="Точка" SuNmb="31" >
<ns3:Ordinate X="483166.05" Y="4192827.37" OrdNmb="1" />
</ns3:SpelementUnit>
<ns3:SpelementUnit TypeUnit="Точка" SuNmb="32" >
<ns3:Ordinate X="483166.45" Y="4192831.64" OrdNmb="1" />
</ns3:SpelementUnit>
<ns3:SpelementUnit TypeUnit="Точка" SuNmb="33" >
<ns3:Ordinate X="483165.85" Y="4192831.75" OrdNmb="1" />
</ns3:SpelementUnit>
<ns3:SpelementUnit TypeUnit="Точка" SuNmb="34" >
<ns3:Ordinate X="483162.82" Y="4192832.33" OrdNmb="1" />
</ns3:SpelementUnit>
<ns3:SpelementUnit TypeUnit="Точка" SuNmb="35" >
<ns3:Ordinate X="483162.81" Y="4192833.5" OrdNmb="1" />
</ns3:SpelementUnit>
<ns3:SpelementUnit TypeUnit="Точка" SuNmb="36" >
<ns3:Ordinate X="483164.6" Y="4192849.37" OrdNmb="1" />
</ns3:SpelementUnit>
<ns3:SpelementUnit TypeUnit="Точка" SuNmb="37" >
<ns3:Ordinate X="483166.52" Y="4192849.15" OrdNmb="1" />
</ns3:SpelementUnit>
<ns3:SpelementUnit TypeUnit="Точка" SuNmb="38" >
<ns3:Ordinate X="483172.31" Y="4192848.47" OrdNmb="1" />
</ns3:SpelementUnit>
<ns3:SpelementUnit TypeUnit="Точка" SuNmb="39" >
<ns3:Ordinate X="483173.7" Y="4192864.09" OrdNmb="1" />
</ns3:SpelementUnit>
<ns3:SpelementUnit TypeUnit="Точка" SuNmb="40" >
<ns3:Ordinate X="483171.9" Y="4192875.11" OrdNmb="1" />
</ns3:SpelementUnit>
<ns3:SpelementUnit TypeUnit="Точка" SuNmb="41" >
<ns3:Ordinate X="483168.57" Y="4192874.56" OrdNmb="1" />
</ns3:SpelementUnit>
<ns3:SpelementUnit TypeUnit="Точка" SuNmb="42" >
<ns3:Ordinate X="483167.52" Y="4192874.68" OrdNmb="1" />
</ns3:SpelementUnit>
<ns3:SpelementUnit TypeUnit="Точка" SuNmb="43" >
<ns3:Ordinate X="483154.44" Y="4192876" OrdNmb="1" />
</ns3:SpelementUnit>
<ns3:SpelementUnit TypeUnit="Точка" SuNmb="44" >
<ns3:Ordinate X="483153.59" Y="4192893.93" OrdNmb="1" />
</ns3:SpelementUnit>
<ns3:SpelementUnit TypeUnit="Точка" SuNmb="45" >
<ns3:Ordinate X="483157.98" Y="4192896.37" OrdNmb="1" />
</ns3:SpelementUnit>
<ns3:SpelementUnit TypeUnit="Точка" SuNmb="46" >
<ns3:Ordinate X="483161.1" Y="4192896.21" OrdNmb="1" />
</ns3:SpelementUnit>
<ns3:SpelementUnit TypeUnit="Точка" SuNmb="47" >
<ns3:Ordinate X="483161.21" Y="4192903.4" OrdNmb="1" />
</ns3:SpelementUnit>
<ns3:SpelementUnit TypeUnit="Точка" SuNmb="48" >
<ns3:Ordinate X="483154.7" Y="4192903.46" OrdNmb="1" />
</ns3:SpelementUnit>
<ns3:SpelementUnit TypeUnit="Точка" SuNmb="49" >
<ns3:Ordinate X="483152" Y="4192911.11" OrdNmb="1" />
</ns3:SpelementUnit>
<ns3:SpelementUnit TypeUnit="Точка" SuNmb="50" >
<ns3:Ordinate X="483154.13" Y="4192916.97" OrdNmb="1" />
</ns3:SpelementUnit>
<ns3:SpelementUnit TypeUnit="Точка" SuNmb="51" >
<ns3:Ordinate X="483157.46" Y="4192920.67" OrdNmb="1" />
</ns3:SpelementUnit>
<ns3:SpelementUnit TypeUnit="Точка" SuNmb="52" >
<ns3:Ordinate X="483161.65" Y="4192922.43" OrdNmb="1" />
</ns3:SpelementUnit>
<ns3:SpelementUnit TypeUnit="Точка" SuNmb="53" >
<ns3:Ordinate X="483164.24" Y="4192933.85" OrdNmb="1" />
</ns3:SpelementUnit>
<ns3:SpelementUnit TypeUnit="Точка" SuNmb="54" >
<ns3:Ordinate X="483164" Y="4192956.08" OrdNmb="1" />
</ns3:SpelementUnit>
<ns3:SpelementUnit TypeUnit="Точка" SuNmb="55" >
<ns3:Ordinate X="483170.67" Y="4192955.65" OrdNmb="1" />
</ns3:SpelementUnit>
<ns3:SpelementUnit TypeUnit="Точка" SuNmb="56" >
<ns3:Ordinate X="483171.08" Y="4192966.27" OrdNmb="1" />
</ns3:SpelementUnit>
<ns3:SpelementUnit TypeUnit="Точка" SuNmb="57" >
<ns3:Ordinate X="483176.35" Y="4193014.35" OrdNmb="1" />
</ns3:SpelementUnit>
<ns3:SpelementUnit TypeUnit="Точка" SuNmb="58" >
<ns3:Ordinate X="483182.48" Y="4193088.15" OrdNmb="1" />
</ns3:SpelementUnit>
<ns3:SpelementUnit TypeUnit="Точка" SuNmb="59" >
<ns3:Ordinate X="483182.67" Y="4193092.46" OrdNmb="1" />
</ns3:SpelementUnit>
<ns3:SpelementUnit TypeUnit="Точка" SuNmb="60" >
<ns3:Ordinate X="483184.87" Y="4193188.96" OrdNmb="1" />
</ns3:SpelementUnit>
<ns3:SpelementUnit TypeUnit="Точка" SuNmb="61" >
<ns3:Ordinate X="483240.04" Y="4193185.74" OrdNmb="1" />
</ns3:SpelementUnit>
<ns3:SpelementUnit TypeUnit="Точка" SuNmb="62" >
<ns3:Ordinate X="483238.96" Y="4193108.24" OrdNmb="1" />
</ns3:SpelementUnit>
<ns3:SpelementUnit TypeUnit="Точка" SuNmb="63" >
<ns3:Ordinate X="483217.77" Y="4192800.31" OrdNmb="1" />
</ns3:SpelementUnit>
<ns3:SpelementUnit TypeUnit="Точка" SuNmb="64" >
<ns3:Ordinate X="483227.48" Y="4192797.5" OrdNmb="1" />
</ns3:SpelementUnit>
<ns3:SpelementUnit TypeUnit="Точка" SuNmb="1" >
<ns3:Ordinate X="483224.7" Y="4192763.93" OrdNmb="1" />
</ns3:SpelementUnit>
</ns3:SpatialElement>
</EntitySpatial>
</SpatialData><CoordSystems>
<ns3:CoordSystem Name="МСК НСО, зона 4" CsId="ID0" />
</CoordSystems>
</CadastralBlock>
</CadastralBlocks>
<CertificationDoc>
<ns6:Organization>ФГИС ЕГРН</ns6:Organization>
<ns6:Date>2019-05-13</ns6:Date>
<ns6:Number>99/2019/261127323</ns6:Number>
</CertificationDoc>
</KPT>
